Chimera_buster/CLI_chimera_buster.py
Chimera_buster/__init__.py
Chimera_buster/chimera_buster.py
Chimera_Buster-1.1.3.dist-info/LICENSE.txt
Chimera_Buster-1.1.3.dist-info/METADATA
Chimera_Buster-1.1.3.dist-info/WHEEL
Chimera_Buster-1.1.3.dist-info/entry_points.txt
Chimera_Buster-1.1.3.dist-info/top_level.txt
Chimera_Buster-1.1.3.dist-info/RECORD
