Metadata-Version: 2.1
Name: Chimera_Buster
Version: 1.1.3
Summary: eliminates chimeric reads by comparing the UMI sequences and finding any matches in the 5 prime or 3 prime UMIs and keeping the sequence that has the highest prevalence
Home-page: https://github.com/JessicaA2019/Chimera_Buster
Author: Jessica Lauren ALbert
Author-email: Jessica Lauren Albert <jessica.albert2001@gmail.com>
License: MIT License
Project-URL: Homepage, https://github.com/JessicaA2019/Chimera_Buster
Keywords: HIV,UMIs,PCR,chimeras,ONT sequencing
Classifier: Programming Language :: Python :: 3
Classifier: License :: OSI Approved :: MIT License
Classifier: Operating System :: OS Independent
Requires-Python: >=3
License-File: LICENSE.txt
